qb/__init__.py
python_qb-1.0.2.dist-info/LICENSE
python_qb-1.0.2.dist-info/METADATA
python_qb-1.0.2.dist-info/WHEEL
python_qb-1.0.2.dist-info/top_level.txt
python_qb-1.0.2.dist-info/RECORD
