Metadata-Version: 2.1
Name: python-qb
Version: 1.0.2
Summary: Quantum Bridge API for Python
Author-email: Pecacheu <3608878+Pecacheu@users.noreply.github.com>
Project-URL: Homepage, https://github.com/Pecacheu/PyQB
Project-URL: Issues, https://github.com/Pecacheu/PyQB/issues
Classifier: Programming Language :: Python :: 3
Classifier: License :: OSI Approved :: GNU General Public License v3 (GPLv3)
Classifier: Operating System :: Microsoft :: Windows
Classifier: Operating System :: POSIX :: Linux
Requires-Python: >=3.10
License-File: LICENSE
